pytams/__init__.py
pytams/bin.py
pytams/database.py
pytams/fmodel.py
pytams/py.typed
pytams/sqldb.py
pytams/tams.py
pytams/taskrunner.py
pytams/trajectory.py
pytams/utils.py
pytams/worker.py
pytams/xmlutils.py
pytams-1.0.0.dist-info/licenses/LICENSE
pytams-1.0.0.dist-info/licenses/NOTICE
pytams-1.0.0.dist-info/METADATA
pytams-1.0.0.dist-info/WHEEL
pytams-1.0.0.dist-info/entry_points.txt
pytams-1.0.0.dist-info/top_level.txt
pytams-1.0.0.dist-info/RECORD
