Metadata-Version: 2.4
Name: pytams
Version: 1.0.0
Summary: An implementation of the trajectory-adaptive multilevel splitting (TAMS) method.
Author-email: Lucas Esclapez <l.esclapez@esciencecenter.nl>
License: 
Project-URL: Repository, https://github.com/nlesc-eTAOC/pyTAMS
Project-URL: Documentation, https://nlesc-etaoc.github.io/pyTAMS/
Project-URL: Issues, https://github.com/nlesc-eTAOC/pyTAMS/issues
Keywords: Rare events,Stochastic systems,Multilevel splitting
Classifier: Development Status :: 4 - Beta
Classifier: Intended Audience :: Science/Research
Classifier: License :: OSI Approved :: Apache Software License
Classifier: Natural Language :: English
Classifier: Programming Language :: Python :: 3
Classifier: Programming Language :: Python :: 3.10
Classifier: Programming Language :: Python :: 3.11
Classifier: Programming Language :: Python :: 3.12
Classifier: Programming Language :: Python :: 3.13
Classifier: Programming Language :: Python :: 3.14
Requires-Python: >=3.10
License-File: LICENSE
License-File: NOTICE
Requires-Dist: toml
Requires-Dist: numpy
Requires-Dist: matplotlib
Requires-Dist: dask
Requires-Dist: dask[distributed]
Requires-Dist: dask-jobqueue
Requires-Dist: SQLAlchemy
Provides-Extra: dev
Requires-Dist: build; extra == "dev"
Requires-Dist: bump-my-version; extra == "dev"
Requires-Dist: coverage[toml]; extra == "dev"
Requires-Dist: pytest; extra == "dev"
Requires-Dist: pytest-cov; extra == "dev"
Requires-Dist: pytest-dependency; extra == "dev"
Requires-Dist: ruff; extra == "dev"
Requires-Dist: mypy; extra == "dev"
Requires-Dist: sphinx; extra == "dev"
Requires-Dist: furo; extra == "dev"
Requires-Dist: sphinx-autoapi; extra == "dev"
Requires-Dist: tox; extra == "dev"
Requires-Dist: myst_parser; extra == "dev"
Provides-Extra: docs
Requires-Dist: sphinx; extra == "docs"
Requires-Dist: furo; extra == "docs"
Requires-Dist: sphinx-autoapi; extra == "docs"
Requires-Dist: myst_parser; extra == "docs"
Provides-Extra: publishing
Requires-Dist: build; extra == "publishing"
Requires-Dist: twine; extra == "publishing"
Requires-Dist: wheel; extra == "publishing"
Provides-Extra: exec
Requires-Dist: netCDF4; extra == "exec"
Requires-Dist: scipy; extra == "exec"
Dynamic: license-file
